{
    "backend": "flask",
    "db_name": "",
    "db_pass": "",
    "db_type": "sqlite",
    "db_user": "",
    "dbms": "1",
    "description": "generated product",
    "design": "soft-ui-dashboard",
    "docker": "1",
    "err_code": 0,
    "frontend": "",
    "heroku": "0",
    "pattern": "mvc",
    "pro": "0",
    "task_id": "0b03fd7e-7436-49f3-95e5-41422ffc02d8",
    "task_info": "Upload Sources [0%] - 334 files",
    "task_output": "0b03fd7e-7436-49f3-95e5-41422ffc02d8.zip",
    "task_result": "SUCCESS",
    "task_state": "RUNNING",
    "task_ts_end": "2023-01-23-17-31-49",
    "task_ts_start": "2023-01-23-17-31-46"
}